ds2ai/ClickAI.py
ds2ai/DS2dataset.py
ds2ai/LabelingAI.py
ds2ai/SkyhubAI.py
ds2ai/__init__.py
ds2ai/util.py
ds2ai-1.1.0.dist-info/LICENSE
ds2ai-1.1.0.dist-info/METADATA
ds2ai-1.1.0.dist-info/WHEEL
ds2ai-1.1.0.dist-info/top_level.txt
ds2ai-1.1.0.dist-info/RECORD
