Metadata-Version: 2.1
Name: ds2ai
Version: 1.1.0
Summary: MLOps Platform - DS2.AI Python SDK
Author: DSLAB GLOBAL, INC
Author-email: contact@dslab.global
License: Apache License 2.0
Platform: UNKNOWN
License-File: LICENSE
